symmetryshift/__init__.py
symmetryshift/_version.py
symmetryshift/cli.py
symmetryshift/create_biological_structure_unit.py
symmetryshift-0.4.0.dist-info/METADATA
symmetryshift-0.4.0.dist-info/WHEEL
symmetryshift-0.4.0.dist-info/entry_points.txt
symmetryshift-0.4.0.dist-info/top_level.txt
symmetryshift-0.4.0.dist-info/RECORD
